{
    "display": {
        "title": {
            "text": "windswept_gravelly_hills"
        },
        "description": {
            "text": "Getting New Biome"
        },
        "icon": {
            "item": "minecraft:gravel"
        },
        "frame": "task",
        "show_toast": false,
        "announce_to_chat": false,
        "hidden": false
    },
    "criteria": {
        "Biome": {
            "trigger": "minecraft:location",
            "conditions": {
                "player": {
                    "location": {
                        "biome": "minecraft:windswept_gravelly_hills",
                        "dimension": "minecraft:overworld"
                    }
                }
            }
        }
    },
    "parent": "ing_advancement:adventure_time/root"
}
