{
    "display": {
        "title": {
            "text": "lukewarm_ocean"
        },
        "description": {
            "text": "Getting New Biome"
        },
        "icon": {
            "item": "minecraft:seagrass"
        },
        "frame": "task",
        "show_toast": false,
        "announce_to_chat": false,
        "hidden": false
    },
    "criteria": {
        "Biome": {
            "trigger": "minecraft:location",
            "conditions": {
                "player": {
                    "location": {
                        "biome": "minecraft:lukewarm_ocean",
                        "dimension": "minecraft:overworld"
                    }
                }
            }
        }
    },
    "parent": "ing:adt_time/root"
}
